doraemon_robotframework-1.6.8.dist-info/METADATA
doraemon_robotframework-1.6.8.dist-info/RECORD
doraemon_robotframework-1.6.8.dist-info/WHEEL
doraemon_robotframework-1.6.8.dist-info/entry_points.txt
doraemon_robotframework-1.6.8.dist-info/top_level.txt
robot/__init__.py
robot/__main__.py
robot/errors.py
robot/jarrunner.py
robot/libdoc.py
robot/pythonpathsetter.py
robot/rebot.py
robot/run.py
robot/testdoc.py
robot/tidy.py
robot/version.py
robot/api/__init__.py
robot/api/deco.py
robot/api/logger.py
robot/conf/__init__.py
robot/conf/gatherfailed.py
robot/conf/settings.py
robot/htmldata/__init__.py
robot/htmldata/htmlfilewriter.py
robot/htmldata/jartemplate.py
robot/htmldata/jsonwriter.py
robot/htmldata/normaltemplate.py
robot/htmldata/template.py
robot/htmldata/common/doc_formatting.css
robot/htmldata/common/js_disabled.css
robot/htmldata/common/storage.js
robot/htmldata/lib/jquery.highlight.min.js
robot/htmldata/lib/jquery.min.js
robot/htmldata/lib/jquery.tablesorter.min.js
robot/htmldata/lib/jquery.tmpl.min.js
robot/htmldata/lib/jsxcompressor.min.js
robot/htmldata/libdoc/libdoc.css
robot/htmldata/libdoc/libdoc.html
robot/htmldata/libdoc/print.css
robot/htmldata/libdoc/pygments.css
robot/htmldata/rebot/common.css
robot/htmldata/rebot/fileloading.js
robot/htmldata/rebot/log.css
robot/htmldata/rebot/log.html
robot/htmldata/rebot/log.js
robot/htmldata/rebot/model.js
robot/htmldata/rebot/print.css
robot/htmldata/rebot/report.css
robot/htmldata/rebot/report.html
robot/htmldata/rebot/testdata.js
robot/htmldata/rebot/util.js
robot/htmldata/rebot/view.js
robot/htmldata/testdoc/testdoc.css
robot/htmldata/testdoc/testdoc.html
robot/libdocpkg/__init__.py
robot/libdocpkg/builder.py
robot/libdocpkg/consoleviewer.py
robot/libdocpkg/htmlwriter.py
robot/libdocpkg/java9builder.py
robot/libdocpkg/javabuilder.py
robot/libdocpkg/model.py
robot/libdocpkg/output.py
robot/libdocpkg/robotbuilder.py
robot/libdocpkg/specbuilder.py
robot/libdocpkg/writer.py
robot/libdocpkg/xmlwriter.py
robot/libraries/BuiltIn.py
robot/libraries/Collections.py
robot/libraries/DateTime.py
robot/libraries/Dialogs.py
robot/libraries/Easter.py
robot/libraries/OperatingSystem.py
